{"cameraMode":{"drawMode":0,"name":"Shaded","section":"Shading Mode"},"sceneLighting":false,"audioPlay":false,"sceneViewState":{"showFog":true,"showMaterialUpdate":false,"showSkybox":false,"showFlares":true,"showImageEffects":true,"showParticleSystems":true},"in2DMode":false,"pivot":{"x":1.1253955364227296,"y":0.37204036116600039,"z":4.3715691566467289},"rotation":{"x":0.008133115246891976,"y":0.991328239440918,"z":-0.10779201239347458,"w":0.07478970289230347},"size":6.6425042152404789,"orthographic":false}